CHANGES.txt
CONTRIBUTORS.txt
MANIFEST.in
README.txt
setup.cfg
setup.py
Products/__init__.py
Products.mediaEvent.egg-info/PKG-INFO
Products.mediaEvent.egg-info/SOURCES.txt
Products.mediaEvent.egg-info/dependency_links.txt
Products.mediaEvent.egg-info/entry_points.txt
Products.mediaEvent.egg-info/namespace_packages.txt
Products.mediaEvent.egg-info/not-zip-safe
Products.mediaEvent.egg-info/paster_plugins.txt
Products.mediaEvent.egg-info/requires.txt
Products.mediaEvent.egg-info/top_level.txt
Products/mediaEvent/README.txt
Products/mediaEvent/__init__.py
Products/mediaEvent/config.py
Products/mediaEvent/configure.zcml
Products/mediaEvent/browser/__init__.py
Products/mediaEvent/browser/configure.zcml
Products/mediaEvent/content/__init__.py
Products/mediaEvent/content/configure.zcml
Products/mediaEvent/content/mediaevent.py
Products/mediaEvent/interfaces/__init__.py
Products/mediaEvent/interfaces/mediaevent.py
Products/mediaEvent/portlets/__init__.py
Products/mediaEvent/portlets/configure.zcml
Products/mediaEvent/profiles/default/factorytool.xml
Products/mediaEvent/profiles/default/metadata.xml
Products/mediaEvent/profiles/default/portlets.xml
Products/mediaEvent/profiles/default/rolemap.xml
Products/mediaEvent/profiles/default/types.xml
Products/mediaEvent/profiles/default/types/Media_Event.xml
Products/mediaEvent/tests/__init__.py
Products/mediaEvent/tests/base.py
Products/mediaEvent/tests/test_doctest.py
docs/HISTORY.txt
docs/INSTALL.txt
docs/LICENSE.GPL
docs/LICENSE.txt