Metadata-Version: 1.0
Name: Products.mediaEvent
Version: 0.11
Summary: Event type with folderish behaviour to store mrelated media
Home-page: http://svn.plone.org/svn/collective/
Author: David Jonas
Author-email: david@intk.com
License: GPL
Keywords: folderish type event
Platform: UNKNOWN
Classifier: Framework :: Plone
Classifier: Intended Audience :: Developers
Classifier: License :: OSI Approved :: GNU General Public License (GPL)
